AUTHORS.txt
INSTALL.txt
LICENSE.txt
MANIFEST.in
README.txt
setup.py
docs/Makefile
docs/conf.py
docs/contents.txt
docs/index.txt
docs/introduction/commerce-tutorial.txt
docs/introduction/index.txt
docs/introduction/installation.txt
docs/introduction/overview.txt
docs/introduction/populate-tutorial.txt
docs/reference/commerce-syntax.txt
docs/reference/commerce-usage.txt
docs/reference/index.txt
docs/reference/populate-syntax.txt
docs/topics/commerce-best-practices.txt
docs/topics/index.txt
rollyourown/__init__.py
rollyourown/commerce/__init__.py
rollyourown/commerce/forms.py
rollyourown/commerce/models.py
rollyourown/commerce/summary.py
rollyourown/commerce/templatetags/__init__.py
rollyourown/commerce/templatetags/currency.py
rollyourown/commerce/utils/__init__.py
rollyourown/commerce/utils/formatting.py
rollyourown/commerce/utils/friendly_id.py
rollyourown_commerce.egg-info/PKG-INFO
rollyourown_commerce.egg-info/SOURCES.txt
rollyourown_commerce.egg-info/dependency_links.txt
rollyourown_commerce.egg-info/namespace_packages.txt
rollyourown_commerce.egg-info/requires.txt
rollyourown_commerce.egg-info/top_level.txt
tests/__init__.py
tests/commerce/__init__.py
tests/commerce/manage.py
tests/commerce/settings.py
tests/commerce/basic/__init__.py
tests/commerce/basic/commerce.py
tests/commerce/basic/forms.py
tests/commerce/basic/models.py
tests/commerce/basic/tests.py