Metadata-Version: 1.0
Name: rollyourown-commerce
Version: 1.0.1
Summary: A framework to ease development of hand rolled ecommerce applications with Django.
Home-page: https://github.com/willhardy/Roll-Your-Own
Author: Will Hardy
Author-email: rollyourown@willhardy.com.au
License: LICENSE.txt
Keywords: ecommerce,django,framework
Platform: UNKNOWN
Classifier: Development Status :: 4 - Beta
Classifier: Environment :: Web Environment
Classifier: Framework :: Django
Classifier: Intended Audience :: Developers
Classifier: Programming Language :: Python
Classifier: License :: OSI Approved :: Apache Software License
Classifier: License :: OSI Approved :: BSD License
Classifier: Operating System :: OS Independent
Classifier: Topic :: Software Development
